GoYuyanRumenZhinan/README.md
GoYuyanRumenZhinan/__init__.py
GoYuyanRumenZhinan/__main__.py
GoYuyanRumenZhinan/file.epub
GoYuyanRumenZhinan/index.html
GoYuyanRumenZhinan/css/__init__.py
GoYuyanRumenZhinan/css/annotations.css
GoYuyanRumenZhinan/css/main.css
GoYuyanRumenZhinan/css/normalize.css
GoYuyanRumenZhinan/css/popup.css
GoYuyanRumenZhinan/font/__init__.py
GoYuyanRumenZhinan/font/fontello.eot
GoYuyanRumenZhinan/font/fontello.svg
GoYuyanRumenZhinan/font/fontello.ttf
GoYuyanRumenZhinan/font/fontello.woff
GoYuyanRumenZhinan/img/__init__.py
GoYuyanRumenZhinan/img/annotator-glyph-sprite.png
GoYuyanRumenZhinan/img/annotator-icon-sprite.png
GoYuyanRumenZhinan/img/apple-touch-icon.png
GoYuyanRumenZhinan/img/cancelfullscreen.png
GoYuyanRumenZhinan/img/close.png
GoYuyanRumenZhinan/img/fullscreen.png
GoYuyanRumenZhinan/img/loader.gif
GoYuyanRumenZhinan/img/menu-icon.png
GoYuyanRumenZhinan/img/save.png
GoYuyanRumenZhinan/img/saved.png
GoYuyanRumenZhinan/img/settings-s.png
GoYuyanRumenZhinan/img/settings.png
GoYuyanRumenZhinan/img/star.png
GoYuyanRumenZhinan/js/__init__.py
GoYuyanRumenZhinan/js/epub.js
GoYuyanRumenZhinan/js/epub.min.js
GoYuyanRumenZhinan/js/epub.min.map
GoYuyanRumenZhinan/js/hooks.min.js
GoYuyanRumenZhinan/js/hooks.min.map
GoYuyanRumenZhinan/js/reader.js
GoYuyanRumenZhinan/js/reader.js.map
GoYuyanRumenZhinan/js/reader.min.js
GoYuyanRumenZhinan/js/reader.min.map
GoYuyanRumenZhinan/js/hooks/__init__.py
GoYuyanRumenZhinan/js/hooks/extensions/__init__.py
GoYuyanRumenZhinan/js/hooks/extensions/highlight.js
GoYuyanRumenZhinan/js/libs/__init__.py
GoYuyanRumenZhinan/js/libs/jquery.min.js
GoYuyanRumenZhinan/js/libs/localforage.min.js
GoYuyanRumenZhinan/js/libs/screenfull.js
GoYuyanRumenZhinan/js/libs/screenfull.min.js
GoYuyanRumenZhinan/js/libs/zip.min.js
GoYuyanRumenZhinan/js/plugins/__init__.py
GoYuyanRumenZhinan/js/plugins/hypothesis.js
GoYuyanRumenZhinan/js/plugins/search.js
go_yuyan_rumen_zhinan-2024.3.5.0.dist-info/METADATA
go_yuyan_rumen_zhinan-2024.3.5.0.dist-info/WHEEL
go_yuyan_rumen_zhinan-2024.3.5.0.dist-info/entry_points.txt
go_yuyan_rumen_zhinan-2024.3.5.0.dist-info/top_level.txt
go_yuyan_rumen_zhinan-2024.3.5.0.dist-info/RECORD
